retryerx/__init__.py
retryerx/decorators.py
tests/__init__.py
tests/test_decorators.py
retryerx-0.1.0.dist-info/LICENSE
retryerx-0.1.0.dist-info/METADATA
retryerx-0.1.0.dist-info/WHEEL
retryerx-0.1.0.dist-info/top_level.txt
retryerx-0.1.0.dist-info/RECORD
