Metadata-Version: 2.1
Name: retryerx
Version: 0.1.0
Summary: A Python library providing retry decorators.
Home-page: https://github.com/ChristianJaimes/retryer
Author: Christian Jaimes Acevedo
Author-email: christiandja@gmail.com
License: MIT
Platform: UNKNOWN
Classifier: Programming Language :: Python :: 3
Classifier: License :: OSI Approved :: MIT License
Classifier: Operating System :: OS Independent
Requires-Python: >=3.6
